shared_architecture/__init__.py
shared_architecture/enums.py
shared_architecture/exceptions.py
shared_architecture/run_all_tests.py
shared_architecture/alerting/alert_manager.py
shared_architecture/auth/__init__.py
shared_architecture/auth/decorators.py
shared_architecture/auth/jwt_manager.py
shared_architecture/auth/middleware.py
shared_architecture/auth/permission_cache.py
shared_architecture/auth/permission_manager.py
shared_architecture/auth/permission_models.py
shared_architecture/auth/user_context.py
shared_architecture/brokers/__init__.py
shared_architecture/bulk_operations/redis_bulk_utils.py
shared_architecture/cache/__init__.py
shared_architecture/clients/__init__.py
shared_architecture/clients/service_client.py
shared_architecture/clients/service_clients.py
shared_architecture/clients/user_service_client.py
shared_architecture/config/__init__.py
shared_architecture/config/config_loader.py
shared_architecture/config/env_validator.py
shared_architecture/config/global_settings.py
shared_architecture/config/redis_cluster_config.py
shared_architecture/config/secrets_manager.py
shared_architecture/config/trade_config.py
shared_architecture/config/validators.py
shared_architecture/connections/__init__.py
shared_architecture/connections/autotrader_pool.py
shared_architecture/connections/connection_manager.py
shared_architecture/connections/enhanced_connection_manager.py
shared_architecture/connections/mongodb_client.py
shared_architecture/connections/rabbitmq_client.py
shared_architecture/connections/redis_client.py
shared_architecture/connections/redis_cluster_manager.py
shared_architecture/connections/service_discovery.py
shared_architecture/connections/timescaledb_client.py
shared_architecture/context/global_app.py
shared_architecture/core/__init__.py
shared_architecture/core/dependencies.py
shared_architecture/core/auth/middleware.py
shared_architecture/core/config/__init__.py
shared_architecture/core/config/base_service_config.py
stocksblitz_shared-0.7.1.dist-info/METADATA
stocksblitz_shared-0.7.1.dist-info/WHEEL
stocksblitz_shared-0.7.1.dist-info/top_level.txt
stocksblitz_shared-0.7.1.dist-info/RECORD
