Metadata-Version: 2.4
Name: stocksblitz-shared
Version: 0.7.1
Summary: Shared Python library for StocksBlitz platform microservices
Home-page: https://github.com/raghurammutya/stocksblitz-platform
Author: Raghuram Mutya
Author-email: raghu.mutya@gmail.com
Project-URL: Bug Tracker, https://github.com/raghurammutya/stocksblitz-platform/issues
Project-URL: Documentation, https://github.com/raghurammutya/stocksblitz-platform/tree/main/shared_architecture
Project-URL: Source Code, https://github.com/raghurammutya/stocksblitz-platform/tree/main/shared_architecture
Keywords: stocksblitz trading microservices shared library architecture
Classifier: Development Status :: 4 - Beta
Classifier: Intended Audience :: Developers
Classifier: Topic :: Software Development :: Libraries :: Python Modules
Classifier: License :: OSI Approved :: MIT License
Classifier: Programming Language :: Python :: 3
Classifier: Programming Language :: Python :: 3.8
Classifier: Programming Language :: Python :: 3.9
Classifier: Programming Language :: Python :: 3.10
Classifier: Programming Language :: Python :: 3.11
Classifier: Operating System :: OS Independent
Classifier: Framework :: FastAPI
Classifier: Topic :: Office/Business :: Financial :: Investment
Requires-Python: >=3.8
Requires-Dist: SQLAlchemy>=2.0.0
Requires-Dist: pydantic>=2.0.0
Requires-Dist: redis>=4.0.0
Requires-Dist: fastapi>=0.100.0
Requires-Dist: circuitbreaker>=1.3.0
Requires-Dist: httpx>=0.25.0
Provides-Extra: dev
Requires-Dist: pytest>=7.0; extra == "dev"
Requires-Dist: pytest-asyncio>=0.21.0; extra == "dev"
Requires-Dist: pytest-cov>=4.0.0; extra == "dev"
Requires-Dist: black>=23.0.0; extra == "dev"
Requires-Dist: isort>=5.12.0; extra == "dev"
Requires-Dist: mypy>=1.0.0; extra == "dev"
Provides-Extra: full
Requires-Dist: psycopg2-binary>=2.9; extra == "full"
Requires-Dist: asyncpg>=0.28.0; extra == "full"
Requires-Dist: aioredis>=2.0.0; extra == "full"
Requires-Dist: python-jose[cryptography]>=3.3.0; extra == "full"
Requires-Dist: passlib[bcrypt]>=1.7.4; extra == "full"
Requires-Dist: uvicorn>=0.20.0; extra == "full"
Requires-Dist: prometheus-fastapi-instrumentator>=6.0.0; extra == "full"
Requires-Dist: celery>=5.3.0; extra == "full"
Dynamic: author
Dynamic: author-email
Dynamic: classifier
Dynamic: description
Dynamic: description-content-type
Dynamic: home-page
Dynamic: keywords
Dynamic: project-url
Dynamic: provides-extra
Dynamic: requires-dist
Dynamic: requires-python
Dynamic: summary
